MANIFEST.in
README.md
pyproject.toml
setup.py
c_src/CMakeLists.txt
c_src/_binding.cc.inc
c_src/binding.cc
c_src/cfg.yaml
c_src/dummy.cc
pylibtooling/__init__.py
pylibtooling.egg-info/PKG-INFO
pylibtooling.egg-info/SOURCES.txt
pylibtooling.egg-info/dependency_links.txt
pylibtooling.egg-info/not-zip-safe
pylibtooling.egg-info/top_level.txt