Metadata-Version: 2.1
Name: pylibtooling
Version: 0.0.0
Summary: A fully featured & always updated python binding for Clang's libtooling.
License: MIT
Project-URL: Homepage, https://github.com/edimetia3d/pylibtooling
Project-URL: Documentation, https://github.com/edimetia3d/pylibtooling
Project-URL: Repository, https://github.com/edimetia3d/pylibtooling
Project-URL: Changelog, https://github.com/edimetia3d/pylibtooling/releases
Keywords: pybind11,libtooling,python,clang,binding
Classifier: Development Status :: 4 - Beta
Classifier: Intended Audience :: Developers
Classifier: License :: OSI Approved :: MIT License
Classifier: Programming Language :: Python :: 3
Classifier: Topic :: Software Development :: Compilers
